{
  "$schema": "https://inlang.com/schema/inlang-message-format",
  "about": "Di",
  "about_built_by": "Creato da <s>un ragazzo che è uno sviluppatore e</s> da alcuni ragazzi che sono sviluppatori per divertimento.",
  "about_check_out": "Guardare",
  "about_for_more_info": "per maggiori informazioni.",
  "about_github_repo": "Repository GitHub",
  "accessory": "Accessorio",
  "actions": "Azioni",
  "active": "Attivo",
  "active_filters_count": "Filtri attivi ( {count} )",
  "active_skill": [
    {
      "declarations": [
        "input count",
        "local countPlural = count: plural"
      ],
      "match": {
        "countPlural=one": "Abilità attiva",
        "countPlural=other": "Competenze attive"
      },
      "selectors": [
        "countPlural"
      ]
    }
  ],
  "activity": "Attività",
  "add": "Aggiungere",
  "add_all_implants": "Aggiungi tutti gli impianti",
  "add_all_pal_gear": "Aggiungi tutto l'equipaggiamento {pal}",
  "add_all_pals_to_entity": "Aggiungi tutti {pals} a {entity}",
  "add_all_skills": "Aggiungi tutte le competenze",
  "add_count_pals": "Aggiungi {count} {type} {pals}",
  "add_entity": "Aggiungi {entity}",
  "add_new_pal": "Aggiungi nuovo {pal}",
  "add_new_pal_to_entity": "Aggiungi un nuovo amico alla tua {entity}",
  "add_new_tag": "Aggiungi nuovo tag",
  "add_notes_about_cloned_pals": "Aggiungi note su questi {pals} clonati...",
  "add_notes_about_imported_pals": "Aggiungi note su questi {pals} importati...",
  "add_other_key_items": "Aggiungi altri elementi chiave",
  "add_pal_to_base": "Aggiungi un nuovo {pal} alla base {base}",
  "add_preset_entity": "Aggiungi il preset {entity}",
  "add_skill": "Aggiungi Inizio",
  "add_skills_preset": "Aggiungi il preset delle competenze {type}",
  "add_tag": "Aggiungi tag",
  "add_to_collection": "Aggiungi alla collezione",
  "add_to_favorites": "Aggiungi ai preferiti",
  "added_label": "Aggiunto:",
  "all": "Tutto",
  "all_entity": "Tutti {entity}",
  "alpha": "Alfa",
  "alpha_pal": "Alpha {pals}",
  "ammo": "Munizioni",
  "ancient_technology_points": "Punti di tecnologia antica",
  "and_more_count": "+ {count} altro",
  "append_to_empty_slots": "Aggiungi gli oggetti del preset agli slot vuoti",
  "apply_preset": "Applica un preset",
  "apply_preset_to_selected": "Applica il preset agli {pals} selezionati",
  "apply_presets": "Applica impostazioni predefinite",
  "apply_selected_entity": "Applica l'entità selezionata {entity}",
  "archive_entity": "Archivio {entity}",
  "armor": "Armatura",
  "attack": "Attacco",
  "available_entity": "Disponibile {entity}",
  "available_saves": "Salvataggi disponibili",
  "available_slots": "Posti disponibili",
  "available_tags": "Tag disponibili",
  "avg_clones_per_pal": "Numero medio di cloni per {pal} :",
  "avg_level": "Livello medio",
  "avg_pals_per_collection": "Media di {pals} per collezione:",
  "avg_transfers_per_pal": "Media trasferimenti per {pal} :",
  "base": [
    {
      "declarations": [
        "input count",
        "local countPlural = count: plural"
      ],
      "match": {
        "countPlural=one": "Base",
        "countPlural=other": "Basi"
      },
      "selectors": [
        "countPlural"
      ]
    }
  ],
  "base_container": "Contenitore base",
  "base_name": "Nome base",
  "base_range": "Gamma base",
  "basecamp_level": "Livello del campo base",
  "blueprint": "Progetto",
  "body": "Corpo",
  "boss": "Capo",
  "box": "Scatola",
  "buildings": "Edifici",
  "bulk_clone_to_ups_failed": "La clonazione in blocco su UPS non è riuscita. Riprova.",
  "cancel": "Cancellare",
  "cannot_fill": "Non puoi riempire il tuo {target} , hai bisogno di {count} slot in più.",
  "cannot_paste_here": "Non è ancora possibile incollare qui™",
  "category": "Categoria",
  "change_player_name": "Cambia il nome del giocatore",
  "changes": "Modifiche",
  "character": "Carattere",
  "character_container": "Logo del personaggio",
  "cheat_mode": "Modalità Trucchi",
  "chest": "Petto",
  "choose_a_entity": "Scegli {entity}",
  "choose_entity": "Seleziona l'entità",
  "clear": "Chiaro",
  "clear_all": "Cancella tutto",
  "clear_all_entity": "Cancella tutto {entity}",
  "clear_completed_missions_confirm": "Sei sicuro di voler cancellare tutte le {count} missioni {type} completate?",
  "clear_current_missions_confirm": "Sei sicuro di voler cancellare tutte le {count} missioni {type} in corso?",
  "clear_entity": "Chiaro {entity}",
  "clear_selected": "Cancella selezionati",
  "clear_selected_entity": "Cancella l'entità selezionata {entity}",
  "clear_selection": "Cancella selezione",
  "cleared_completed_missions": "Missioni completate {count} e portate a termine {type}",
  "cleared_current_missions": "Missioni {type} {count} .",
  "click_map_coordinates": "Clicca sulla mappa per visualizzare le coordinate dettagliate.",
  "click_to_complete": "Fare clic per completare",
  "click_toggle_point": "Fai clic su un punto di viaggio rapido o su un'effigie per attivarlo/disattivarlo per il giocatore selezionato.",
  "clipboard_cleared": "Appunti svuotati",
  "clone_pal_to_entity": "Clona {pal} in {entity}",
  "clone_pals_to_entity": "Clona {count} {pals} in {entity}",
  "clone_prefix": "Prefisso del clone",
  "clone_selected_pal": "Clone selezionato {pal}",
  "clone_to_entity": "Clona in {entity}",
  "clone_to_entity_failed": "La clonazione di {entity} non è riuscita. Riprova.",
  "clones": "Cloni",
  "cloning_count_pals": "Clonazione {count} {pals}",
  "close_drawer": "Chiudi cassetto",
  "close_toast": "Brindisi ravvicinato",
  "collect_all_effigies": "Colleziona tutte le effigi",
  "collected": "Raccolto",
  "collection": [
    {
      "declarations": [
        "input count",
        "local countPlural = count: plural"
      ],
      "match": {
        "countPlural=one": "Collezione",
        "countPlural=other": "Collezioni"
      },
      "selectors": [
        "countPlural"
      ]
    }
  ],
  "collection_delete_warning": "Gli amici presenti in questa raccolta non verranno eliminati, ma non saranno più associati a questa raccolta.",
  "collection_name": "vita della raccolta",
  "collection_optional": "Raccolta (facoltativa)",
  "collections": "Collezioni",
  "common": "Comune",
  "completed": "Completato",
  "completed_missions": "Missioni completate",
  "confirm": "Confermare",
  "consume": "Consumabile",
  "container_entity": "Contenitore {entity}",
  "copy": "Copia",
  "create": "Creare",
  "create_entity_name": "Crea \" {name} \" {entity}",
  "create_first_entity": "Crea la tua prima {entity}",
  "create_new_collection": "Crea una nuova collezione",
  "create_pals_or_import": "Crea nuovi {pals} o importali dai tuoi file di salvataggio per iniziare.",
  "create_preset_from_container": "Crea preset dal contenitore",
  "create_preset_from_current": "Crea un preset dall'entità corrente {entity}",
  "created": "Creato",
  "current_collection": "Collezione attuale",
  "current_missions": "Missioni in corso",
  "current_save_file": "File di salvataggio corrente",
  "debug": "Debug",
  "docs": "Documenti",
  "docs_wiki": "Wiki",
  "docs_guides": "Guide",
  "docs_tours": "Tour",
  "docs_wiki_description": "Consulta tutti i dati di gioco, inclusi amici, oggetti, edifici, abilità e altro ancora.",
  "docs_guides_description": "Guide scritte per l'utilizzo dell'applicazione.",
  "docs_tours_description": "Guide interattive che illustrano le funzionalità dell'applicazione.",
  "docs_search_placeholder": "Ricerca...",
  "docs_no_results": "Nessun risultato trovato.",
  "docs_start_tour": "Avvia il tour",
  "docs_tour_requires_save": "Richiede il caricamento di un file di salvataggio.",
  "debug_mode": "Modalità di debug",
  "defense": "Difesa",
  "delete": "Eliminare",
  "delete_count_entities_confirm": "Sei sicuro di voler eliminare le {count} {entity} selezionate?",
  "delete_entire_guild": "Elimina l'intera gilda",
  "delete_entity": "Elimina {entity}",
  "delete_entity_by_name_confirm": "Sei sicuro di voler eliminare {name} ? Questa azione non può essere annullata.",
  "delete_entity_confirm": "Sei sicuro di voler eliminare questa {entity} ? Questa azione non può essere annullata.",
  "delete_entity_warning": "Sei sicuro di voler eliminare \" {name} \"? {warning}",
  "delete_selected_entity": "Elimina l'entità selezionata {entity}",
  "delete_selected_entity_confirm": "Sei sicuro di voler eliminare l' {entity} selezionata?",
  "deleted_entity": "Eliminati {count} {entity}",
  "description_optional": "Descrizione (facoltativa)",
  "dimensional_pal_storage": "Archiviazione dimensionale {pal}",
  "distribution": "Distribuzione",
  "download": "Scaricamento",
  "download_modified_save": "Scarica il file Level.sav modificato",
  "dps": "DPS",
  "dps_not_available": "Il giocatore selezionato non ha un DPS",
  "drag_drop_zip": "oppure trascina e rilascia qui il tuo file zip",
  "dungeons": "Sotterranei",
  "edit": "Modificare",
  "edit_entity": "Modifica {entity}",
  "edit_entity_name": "Modifica il nome {entity}",
  "edit_tags_for_pals": "Modifica i tag per {count} {pals}",
  "editor": "Redattore",
  "effect": "Effetto",
  "effigies": "Effigi di Lifmunk",
  "effigy": "Effigie di Lifmunk",
  "egg": "Uovo",
  "element_and_type": "Elemento e tipo",
  "element_types": "Tipi di elementi",
  "elemental_distribution": "Distribuzione elementare",
  "elements": "Elementi",
  "empty": "Vuoto",
  "enter_item_count": "Inserisci il numero di articoli",
  "enter_name_for_entity": "Inserisci un nome per la nuova {entity} :",
  "enter_new_name_for_entity": "Inserisci il nuovo nome per l' {entity} :",
  "enter_tag_name": "Inserisci il nome del tag",
  "entity_count_available": "{count} {entity} disponibile",
  "entity_not_available": "{entity} non è disponibile.",
  "epic": "Epico",
  "error": "Errore",
  "error_copied": "Dettagli dell'errore copiati negli appunti",
  "error_copy_failed": "Impossibile copiare i dettagli dell'errore",
  "error_nuke_operation": "Si è verificato un errore durante l'operazione nucleare. Riprova.",
  "essential": "Essenziale",
  "export": "Esportare",
  "export_note_message": "Gli amici esportati verranno copiati nella posizione di destinazione. Gli originali rimarranno presso UPS.",
  "export_pals": "Esporta {count} {pals}",
  "export_preset": "Esporta il preset in un file",
  "export_selected": "Esporta selezionato",
  "export_target": "Obiettivo di esportazione",
  "export_to": "Esporta a",
  "export_to_target": "Esporta in {target}",
  "exporting_count_selected_pals": "Esportazione di {count} selezionati {pals}",
  "failed_create_pal": "Impossibile creare un nuovo amico. Riprova.",
  "failed_export_pals": "Impossibile esportare {count} {pals}",
  "failed_get_pal_data": "Impossibile ottenere i dati PAL",
  "failed_nuke_ups": "Impossibile distruggere UPS. Riprova.",
  "fast_travel": "Viaggio veloce",
  "favorites": "Preferiti",
  "feed": "Foraggio",
  "file": [
    {
      "declarations": [
        "input count",
        "local countPlural = count: plural"
      ],
      "match": {
        "countPlural=one": "File",
        "countPlural=other": "File"
      },
      "selectors": [
        "countPlural"
      ]
    }
  ],
  "fill": "Riempire",
  "fill_container": "Contenitore per bombole",
  "fill_current_entity": "Inserisci l'entità corrente {entity}",
  "fill_entity": "Riempi {entity}",
  "filter": [
    {
      "declarations": [
        "input count",
        "local countPlural = count: plural"
      ],
      "match": {
        "countPlural=one": "Filtro",
        "countPlural=other": "Filtri"
      },
      "selectors": [
        "countPlural"
      ]
    }
  ],
  "filter_and_sort": "Filtra e ordina",
  "filtered": "Filtrato",
  "food": "Cibo",
  "for": "per",
  "friendship_rank": "Grado di amicizia",
  "gender": "Genere",
  "glider": "Aliante",
  "global_pal_storage": "Archiviazione globale {pal}",
  "gps": "GPS",
  "gps_not_available": "Il GPS non è disponibile in questo file di salvataggio.",
  "grid_view": "Visualizzazione a griglia",
  "guild": [
    {
      "declarations": [
        "input count",
        "local countPlural = count: plural"
      ],
      "match": {
        "countPlural=one": "Gilda",
        "countPlural=other": "Gilde"
      },
      "selectors": [
        "countPlural"
      ]
    }
  ],
  "guild_name": "Nome della gilda",
  "head": "Testa",
  "heal_all_in_entity": "Guarisci tutto in {entity}",
  "heal_selected_pals": "Guarisci i {pals} selezionati",
  "health": "Salute",
  "how_many_clones": "Quanti cloni?",
  "hp": "HP",
  "human": [
    {
      "declarations": [
        "input count",
        "local countPlural = count: plural"
      ],
      "match": {
        "countPlural=one": "Umano",
        "countPlural=other": "Esseri umani"
      },
      "selectors": [
        "countPlural"
      ]
    }
  ],
  "id": "ID",
  "import": "Importare",
  "import_failed": "Importazione non riuscita. Riprova.",
  "import_from": "Importa da",
  "import_from_save": "Importa da Salva",
  "import_preset": "Importa preset da file",
  "import_to_ups_message": "Seleziona la fonte e le opzioni per importare {pals} in UPS.",
  "import_to_ups_title": "Salva il file su UPS",
  "in_inventory": "in inventario",
  "info": "Informazioni",
  "invalid_option_selected": "Opzione selezionata non valida",
  "inventory": "Inventario",
  "item": [
    {
      "declarations": [
        "input count",
        "local countPlural = count: plural"
      ],
      "match": {
        "countPlural=one": "Articolo",
        "countPlural=other": "Elementi"
      },
      "selectors": [
        "countPlural"
      ]
    }
  ],
  "item_container": "Contenitore per articoli",
  "item_copied": "{name} copiato negli appunti",
  "ivs": "flebo",
  "key_items": "Elementi chiave",
  "lab": "Laboratorio",
  "language": "Lingua",
  "last_accessed": "Ultimo accesso",
  "last_online": "Ultimo aggiornamento online",
  "last_updated_date": "Ultimo aggiornamento: {date}",
  "later": "Dopo",
  "learn_all_skills": "Impara tutte le abilità",
  "learn_skills_matching_type": "Impara tutte le abilità Abbinamento con il tipo di amico",
  "learned_skills": "Competenze acquisite",
  "left_click_focus": "Fai clic con il pulsante sinistro del mouse su un giocatore o una base per selezionare il bersaglio.",
  "legendary": "Leggendario",
  "level": "Livello",
  "level_abbr": "Livello",
  "level_abbr_value": "Livello {value}",
  "level_distribution": "Distribuzione dei livelli",
  "level_sync_display": "Sincronizzazione del livello {from} → {to}",
  "level_value": "Livello {level}",
  "list_view": "Visualizzazione elenco",
  "load_guild_bases": "Carica gilde/basi",
  "load_player": "Carica il giocatore",
  "loaded_entity": "Caricata {entity}",
  "loading_data": "Caricamento dati in corso...",
  "loading_entity": "Caricamento di {entity}",
  "loadout": "Equipaggiamento",
  "location": "Posizione",
  "lock_all": "Blocca tutto",
  "locked": "Chiuso",
  "lucky": "Fortunato",
  "lucky_pals": "{pals} fortunati",
  "main_missions": "Missioni principali",
  "manage_collection_for_pals": "Gestisci la collezione per {count} {pals}",
  "map": "Mappa",
  "map_coordinate_origin_point": "punto di origine delle coordinate sulla mappa",
  "map_coordinates": "Coordinate sulla mappa",
  "map_options": "Opzioni mappa",
  "mark_all_current_complete": "Contrassegna tutte le voci correnti come completate",
  "mark_complete": "Contrassegna come completato",
  "mark_complete_confirm": "Sei sicuro di voler contrassegnare come completate tutte le {count} missioni {type} attualmente in corso?",
  "marked_missions_complete": "Sono state contrassegnate {count} {type} missioni come completate",
  "material": "Materiale",
  "max": "Massimo",
  "max_ivs": "Massimizzare le IV",
  "max_level": "Livello massimo",
  "max_level_pals": "Livello massimo {pals}",
  "max_out_pal_stats": "Massimizza le statistiche {pal} 💉💪",
  "max_out_selected_pals": "Massimizza {pals} selezionati",
  "max_souls": "Massimizza le anime",
  "max_work_suitability": "Massimizzare l'idoneità al lavoro",
  "menu": "Menu",
  "min_level": "Livello minimo",
  "mission": "Missione",
  "mission_cleared": "Missione compiuta",
  "mission_marked_complete": "Missione contrassegnata come completata",
  "missions": "Missioni",
  "mixed_collections": "Collezioni miste",
  "mixed_collections_message": "{pals} selezionati sono in collezioni diverse oppure alcuni non hanno una collezione",
  "modified": "Modificato",
  "modified_label": "Modificato:",
  "module": "Modulo",
  "monster_equip_weapon": "Equipaggiamento del mostro Arma",
  "most_popular": "Più popolari",
  "move": "Mossa",
  "move_all_to_collection": "Sposta tutti {pals} selezionati in \" {name} \"",
  "move_to_entity": "Spostati in {entity}",
  "moved_pals_to_collection": "Spostati {count} {pals} nella collezione",
  "name": "Nome",
  "new_pal_prefix": "Nuovo prefisso Pal",
  "new_version_available": "Una nuova versione di Palworld Save Pal è disponibile su GitHub.",
  "next": "Prossimo",
  "nickname": "Soprannome",
  "no_archived_entity": "Nessun {entity} archiviata",
  "no_bases_loaded": "Nessuna base caricata al momento. Utilizza il selettore di gilde qui sopra per caricare le basi.",
  "no_changes": "Nessuna modifica",
  "no_collection": "Nessuna raccolta",
  "no_completed_missions_to_clear": "Nessuna missione completata da sbloccare",
  "no_current_missions_to_clear": "Nessuna missione da completare al momento",
  "no_current_missions_to_complete": "Nessuna missione da completare al momento",
  "no_detailed_info": "Non sono disponibili informazioni dettagliate.",
  "no_entity_matching": "Nessuna {entity} trovata corrispondente a \" {query} \"",
  "no_entity_selected": "Nessuna {entity} selezionata",
  "no_entity_yet": "Nessuna {entity} ancora",
  "no_guild_bases_found": "Nessuna base di gilda trovata",
  "no_guild_found": "Nessuna gilda trovata",
  "no_level_sync": "Nessuna sincronizzazione di livello",
  "no_missions_found": "Nessuna missione {type} trovata",
  "no_pals_available": "Nessun dato {pals} disponibile",
  "no_pals_in_storage": "Nessun {pals} in magazzino",
  "no_players_loaded": "Nessun giocatore caricato al momento. Utilizza il selettore qui sopra per caricare i giocatori.",
  "no_save_loaded": "Nessun file di salvataggio caricato",
  "no_skills_learned": "Nessuna competenza appresa",
  "no_slots_available_in_entity": "Non ci sono slot disponibili in questa {entity} .",
  "no_storage_containers": "Nessun contenitore di stoccaggio",
  "none": "Nessuno",
  "not_collected": "Non raccolto",
  "normal": "Normale",
  "note": "Nota",
  "notes_optional": "Note (facoltative)",
  "nuke_all_presets": "Elimina tutte le impostazioni predefinite",
  "nuke_presets_confirm": "Sei sicuro di voler eliminare tutte le impostazioni predefinite? Questa azione ripristinerà le impostazioni predefinite e non potrà essere annullata.",
  "nuke_ups": "Nuke UPS - Elimina TUTTI {pals}",
  "of": "Di",
  "oil_rig": "Piattaforma petrolifera",
  "oil_rig_pals": "Piattaforma petrolifera {pals}",
  "oops_something_wrong": "Ops... Qualcosa è andato storto",
  "open_drawer": "Apri il cassetto",
  "open_folder": "Apri la cartella",
  "or_drag_and_drop": "oppure trascina e rilascia",
  "origin": "Origine",
  "origin_label": "Fonte:",
  "origin_point": "Origine (0,0)",
  "page": "Pagina",
  "page_of_pages": "Pagina {current} di {total}",
  "pal": [
    {
      "declarations": [
        "input count",
        "local countPlural = count: plural"
      ],
      "match": {
        "countPlural=one": "Amico",
        "countPlural=other": "Pals"
      },
      "selectors": [
        "countPlural"
      ]
    }
  ],
  "pal_box_party": "Palbox + festa",
  "pal_cannot_be_trait": "{type} Pal non può essere {trait}",
  "pal_types": "Tipi di Pal",
  "palbox": "Palbox",
  "paldeck": "Paldeck",
  "pals_in_storage": "{pals} in magazzino",
  "party": "Festa",
  "passive": "Passivo",
  "passive_skill": [
    {
      "declarations": [
        "input count",
        "local countPlural = count: plural"
      ],
      "match": {
        "countPlural=one": "Abilità passiva",
        "countPlural=other": "Abilità passive"
      },
      "selectors": [
        "countPlural"
      ]
    }
  ],
  "paste": "Impasto",
  "player": [
    {
      "declarations": [
        "input count",
        "local countPlural = count: plural"
      ],
      "match": {
        "countPlural=one": "Giocatore",
        "countPlural=other": "Giocatori"
      },
      "selectors": [
        "countPlural"
      ]
    }
  ],
  "predator": "Predatore",
  "predator_pals": "Predatore {pals}",
  "preset": [
    {
      "declarations": [
        "input count",
        "local countPlural = count: plural"
      ],
      "match": {
        "countPlural=one": "Preimpostazione",
        "countPlural=other": "Preimpostazioni"
      },
      "selectors": [
        "countPlural"
      ]
    }
  ],
  "preset_name": "Nome predefinito",
  "preset_select_details": "Seleziona un preset dall'elenco per visualizzarne i dettagli.",
  "presets_precedence": "L'ordine di precedenza dei preset è: blocco PAL ➡️ blocco elemento ➡️ predefinito. Selezionare un solo preset per PAL, elemento o predefinito.",
  "previous": "Precedente",
  "progress": "Progressi",
  "pwr": "Potenza",
  "raid": "Incursione",
  "range": "Allineare",
  "rare": "Raro",
  "raw": "Crudo",
  "read_only": "SOLA LETTURA",
  "ready_to_fill": "Pronto a riempire {target} con {count} {pals} .",
  "refresh": "Aggiorna (Annulla le modifiche non salvate)",
  "refresh_entity": "Aggiorna {entity}",
  "remove": "Rimuovere",
  "remove_all_from_collections": "Rimuovi tutti {pals} selezionati dalle loro collezioni",
  "remove_from_collection": "Rimuovi dalla collezione",
  "remove_from_favorites": "Rimuovi dai preferiti",
  "remove_pal": "Rimuovi Pal",
  "removed_pals_from_collections": "Rimossi {count} {pals} dalle collezioni",
  "research_cost": "Costo della ricerca",
  "research_node": "Nodo di ricerca",
  "reset": "Reset",
  "restore_hp": "Ripristina HP",
  "rewards": "Premi",
  "right_click_edit_base": "Fai clic con il pulsante destro del mouse su una base per modificarne il nome.",
  "save": [
    {
      "declarations": [
        "input count",
        "local countPlural = count: plural"
      ],
      "match": {
        "countPlural=one": "Salva",
        "countPlural=other": "Salvataggi"
      },
      "selectors": [
        "countPlural"
      ]
    }
  ],
  "save_as_preset": "Salva come predefinito",
  "save_changes": "Salva le modifiche",
  "save_file_to_ups": "Salva file 🡆 UPS",
  "save_id": "Salva ID",
  "save_platform": "Piattaforma di salvataggio",
  "search": "Ricerca",
  "search_by_name_nickname": "Cerca per nome o soprannome",
  "search_entity": "Cerca {entity}",
  "search_pals": "Cerca {pals} per nome, ID del personaggio o note...",
  "search_placeholder": "Cerca {entity} ...",
  "search_presets": "Cerca preset",
  "select": "Selezionare",
  "select_a_entity": "Seleziona {entity}",
  "select_a_entity_to_view": "Seleziona {entity} per visualizzarne i dettagli.",
  "select_all_current_base": "Seleziona tutto nella base corrente",
  "select_all_filtered_pals": "Seleziona tutti {pals} filtrati ( {count} )",
  "select_all_in": "Seleziona tutto in",
  "select_all_page_pals": "Seleziona tutti {pals} nella pagina corrente ( {count} )",
  "select_all_ups_pals": "Seleziona tutti {pals} in UPS ( {count} )",
  "select_entity": "Seleziona {entity}",
  "select_entity_to_edit": "Seleziona {entity} da modificare",
  "select_entity_to_load": "Seleziona {entity} da caricare e visualizzare sulla mappa.",
  "select_guild_to_load_bases": "Seleziona una gilda per caricare le sue basi sulla mappa",
  "select_pal_edit_description": "{pals} possono essere selezionati nella Cassa degli amici del giocatore, nelle Basi della gilda, nel Deposito amici globale, nel Deposito amici dimensionale o nel Deposito amici universale",
  "select_player_view_entity": "Seleziona un giocatore per visualizzare {entity}",
  "select_valid_player": "Seleziona un giocatore valido",
  "selected": "Selezionato",
  "selected_of_total": "{selected} di {total} selezionati",
  "selected_tags": "Tag selezionati",
  "set_entity_item_count": "Imposta il conteggio degli elementi {entity}",
  "set_inventory_count": "Imposta il conteggio dell'inventario",
  "set_item_count": "Imposta il numero di elementi",
  "settings": "Impostazioni",
  "shield": "Scudo",
  "shortcuts": "Scorciatoie",
  "show_archived": "Mostra archiviati",
  "showing_pals": "Visualizzazione {start} a {end} di {total} {pals}",
  "size": "Misurare",
  "skills": "Competenze",
  "slots_available_in_entity": "In questa {entity} sono disponibili {count} slot.",
  "sort": "Ordinare",
  "sort_by": "Ordina per",
  "sort_by_entity": "Ordina per {entity}",
  "sort_inventory": "Ordina l'inventario",
  "souls": "Anime",
  "special_categories": "Categorie speciali",
  "special_weapon": "Arma speciale",
  "sphere_module": "Modulo sferico",
  "stamina": "Resistenza",
  "statistics": "Statistiche",
  "stats": "Statistiche",
  "steam": "Vapore",
  "steam_description": "Steam/Mac: file di salvataggio Level.sav",
  "stomach": "Stomaco",
  "storage": "Magazzinaggio",
  "storage_container": "Contenitore per stoccaggio",
  "structures": "Strutture",
  "sub_missions": "Sotto-missioni",
  "success": "Successo",
  "successfully_cloned_pal_to_entity": "Clonazione {pal} in {entity} completata con successo.",
  "successfully_cloned_pals_to_entity": "Clonazione {count} {pals} in {entity} completata con successo.",
  "successfully_deleted_entity": "Eliminazione completata con successo {count} {pals} da {entity}",
  "successfully_exported_pals": "Esportazione completata con successo di {count} di {total} {pals}",
  "summon": "Convocare",
  "summoned": "Evocato",
  "summoned_pals": "Evocati {pals}",
  "support": "Supporto",
  "syncing": "Sincronizzazione",
  "tag": [
    {
      "declarations": [
        "input count",
        "local countPlural = count: plural"
      ],
      "match": {
        "countPlural=one": "Etichetta",
        "countPlural=other": "Etichette"
      },
      "selectors": [
        "countPlural"
      ]
    }
  ],
  "tag_changes": "Modifiche ai tag",
  "tag_delete_warning": "Questo tag verrà rimosso da tutti gli amici che lo possiedono.",
  "tags_for_pals": "Tag per {count} {pals}",
  "tags_optional": "Tag (facoltativi)",
  "talents_ivs": "Talenti (IV)",
  "target_available": "Target è disponibile",
  "technology": [
    {
      "declarations": [
        "input count",
        "local countPlural = count: plural"
      ],
      "match": {
        "countPlural=one": "Tecnologia",
        "countPlural=other": "Tecnologie"
      },
      "selectors": [
        "countPlural"
      ]
    }
  ],
  "technology_points": "Punti tecnologici",
  "theme": "Tema",
  "to_collection": "alla raccolta",
  "toggle_entity": "Attiva/disattiva {entity}",
  "tools": "Utensili",
  "tools_convert_save": "Converti Salva Formato",
  "tools_convert_save_description": "Converti i file di salvataggio tra i formati Steam e Xbox Game Pass.",
  "tools_convert_loaded": "Converti Caricato Salva",
  "tools_convert_standalone": "Converti file di salvataggio",
  "tools_select_source": "Seleziona la fonte",
  "tools_select_output": "Seleziona l'output",
  "tools_source_format": "Formato sorgente",
  "tools_target_format": "Formato di destinazione",
  "total": "Totale",
  "total_clones": "Total Clones",
  "total_count": "Conteggio totale",
  "total_exports": "Esportazioni totali",
  "total_pals": "Totale {pals}",
  "transfer": [
    {
      "declarations": [
        "input count",
        "local countPlural = count: plural"
      ],
      "match": {
        "countPlural=one": "Trasferire",
        "countPlural=other": "Trasferimenti"
      },
      "selectors": [
        "countPlural"
      ]
    }
  ],
  "transfer_all_pals": "Trasferisci tutti {pals}",
  "transfer_pal": "Trasferimento {pal}",
  "trust": "Fiducia",
  "trust_level": "Livello di fiducia",
  "trust_xp": "Affidati a XP",
  "type": [
    {
      "declarations": [
        "input count",
        "local countPlural = count: plural"
      ],
      "match": {
        "countPlural=one": "Tipo",
        "countPlural=other": "Dimensioni"
      },
      "selectors": [
        "countPlural"
      ]
    }
  ],
  "type_label": "Tipo: {type}",
  "unarchive_entity": "Decomprimi {entity}",
  "uncommon": "Non comune",
  "universal_pal_storage": "Archiviazione universale {pal}",
  "unknown": "Sconosciuto",
  "unknown_collection": "Collezione sconosciuta",
  "unlock_all": "Sblocca tutto",
  "unlock_all_category_research": "Sblocca tutte le ricerche {category}",
  "unlock_all_fast_travel": "Sblocca tutti i punti di viaggio rapido",
  "unlock_full_map": "Sblocca la mappa completa",
  "unlock_map": "Sblocca la mappa",
  "unlock_map_confirm": "Questo sbloccherà l'intera mappa modificando il file LocalData.sav. Dovrai selezionare il file LocalData.sav. Continuare?",
  "unlock_prerequisite_entity": "Sblocca prima il prerequisito {entity}",
  "unlocked": "Sbloccato",
  "unlocks": "Sblocca",
  "update_available": "Aggiornamento disponibile!",
  "update_now": "Aggiorna ora",
  "updated_tags_for_pals": "Tag aggiornati per {count} {pals}",
  "upload": "Caricamento",
  "upload_a_file": "Carica un file",
  "upload_zip_files": "Fai clic per caricare i tuoi file di salvataggio compressi",
  "ups": "UPS",
  "ups_already_empty": "UPS era già vuoto",
  "used_slots": "Slot usati",
  "warning": "Avvertimento",
  "weapon": [
    {
      "declarations": [
        "input count",
        "local countPlural = count: plural"
      ],
      "match": {
        "countPlural=one": "Arma",
        "countPlural=other": "Armi"
      },
      "selectors": [
        "countPlural"
      ]
    }
  ],
  "weight": "Peso",
  "work_speed": "Velocità di lavoro",
  "work_suitability": "Idoneità al lavoro",
  "working_on_it": "Beep Boop, ci stiamo lavorando!",
  "workload": "Carico di lavoro",
  "workspeed": "Velocità di lavoro",
  "world_coordinates": "Coordinate mondiali",
  "world_name": "Nome del mondo",
  "xbox_game_pass": "Xbox Game Pass",
  "xbox_game_pass_description": "Xbox Game Pass: file container.index",
  "zoom_in_out": "Zoom avanti/indietro"
}
